LICENSE.txt
MANIFEST.in
README.md
VERSION
setup.cfg
setup.py
khaos/__init__.py
khaos.egg-info/PKG-INFO
khaos.egg-info/SOURCES.txt
khaos.egg-info/dependency_links.txt
khaos.egg-info/top_level.txt