Metadata-Version: 2.1
Name: khaos
Version: 0.0.1
Summary: khaos
Home-page: https://gitee.com/chaos-god/khaos.git
Author: khaos
Author-email: 9239867+chaos-god@user.noreply.gitee.com
License: UNKNOWN
Platform: UNKNOWN
License-File: LICENSE.txt
